LICENSE
MANIFEST.in
README.md
pyproject.toml
setup.cfg
kanji_to_time/__init__.py
kanji_to_time/convert_table.py
kanji_to_time.egg-info/PKG-INFO
kanji_to_time.egg-info/SOURCES.txt
kanji_to_time.egg-info/dependency_links.txt
kanji_to_time.egg-info/requires.txt
kanji_to_time.egg-info/top_level.txt
kanji_to_time/grammer/kanji_to_time.lark
kanji_to_time/transformer/BaseTransformer.py
kanji_to_time/transformer/DatetimeTransformer.py
kanji_to_time/transformer/TimedeltaTransformer.py
kanji_to_time/transformer/__init__.py
tests/test_to_datetime.py
tests/test_to_number.py
tests/test_to_timedelta.py