Metadata-Version: 2.1
Name: kanji_to_time
Version: 0.0.3
Summary: Convert Japanese time expressions to datetime objects
Home-page: https://github.com/corkborg/kanji_to_time
Author: corkborg
Author-email: ax4squil8@mozmail.com
License: MIT
Keywords: kanji,timedelta,datetime,japanese
Classifier: Development Status :: 4 - Beta
Classifier: Intended Audience :: Developers
Classifier: License :: OSI Approved :: MIT License
Classifier: Programming Language :: Python :: 3.11
Classifier: Natural Language :: Japanese
License-File: LICENSE
Requires-Dist: lark>=1.1.9
